orgminer/__init__.py
orgminer-0.1.0.dist-info/METADATA
orgminer-0.1.0.dist-info/WHEEL
orgminer-0.1.0.dist-info/top_level.txt
orgminer-0.1.0.dist-info/RECORD
