Metadata-Version: 2.1
Name: orgminer
Version: 0.1.0
Summary: [LEGACY] Python toolkit for organizational mining, now maintained as "OrdinoR"
Home-page: https://github.com/roy-jingyang/OrgMiner
Author: Jing (Roy) Yang
Author-email: roy.j.yang@qut.edu.au
License: UNKNOWN
Platform: UNKNOWN
Requires-Python: >=3.7
Requires-Dist: ordinor
